pylintconfig/__init__.py
pylintconfig/disable.py
pylintconfig/ignore.py
pylintconfig/pylintconfig.py
pylintconfig/version.py
pylintconfig-0.1.1.dist-info/METADATA
pylintconfig-0.1.1.dist-info/RECORD
pylintconfig-0.1.1.dist-info/WHEEL
pylintconfig-0.1.1.dist-info/entry_points.txt
pylintconfig-0.1.1.dist-info/top_level.txt
