Metadata-Version: 2.1
Name: pylintconfig
Version: 0.1.1
Summary: cli for easy configuration of pylint
Home-page: https://github.com/GliderGeek/pylintconfig
License: UNKNOWN
Platform: UNKNOWN
Requires-Dist: Click
Requires-Dist: pylint
